socho/__init__.py
socho/cli.py
socho/profile.py
socho-1.3.3.dist-info/LICENSE.txt
socho-1.3.3.dist-info/METADATA
socho-1.3.3.dist-info/WHEEL
socho-1.3.3.dist-info/entry_points.txt
socho-1.3.3.dist-info/top_level.txt
socho-1.3.3.dist-info/RECORD
