Metadata-Version: 2.1
Name: socho
Version: 1.3.3
Summary: Social choice functions and CLI tool
Home-page: https://github.com/qpwo/socho
Author: Luke Harold Miles, Bernardo Trevizan
Author-email: lukem@sent.com, trevizanbernardo@gmail.com
License: UNKNOWN
Platform: UNKNOWN
License-File: LICENSE.txt
Requires-Dist: numpy
Requires-Dist: pandas
